nexsys-0.0.2.dist-info/METADATA
nexsys-0.0.2.dist-info/WHEEL
nexsys/__init__.py
nexsys/ffi.py
nexsys/native.so
nexsys-0.0.2.dist-info/RECORD
