Metadata-Version: 2.1
Name: nexsys
Version: 0.0.2
Summary: Solve nonlinear systems of equations using Newton's method.
License: GPL-3.0-or-later
